hashfile/__init__.py
hashfile-2.1.5.dist-info/DESCRIPTION.rst
hashfile-2.1.5.dist-info/METADATA
hashfile-2.1.5.dist-info/RECORD
hashfile-2.1.5.dist-info/WHEEL
hashfile-2.1.5.dist-info/entry_points.txt
hashfile-2.1.5.dist-info/metadata.json
hashfile-2.1.5.dist-info/top_level.txt
