Metadata-Version: 2.0
Name: hashfile
Version: 2.1.5
Summary: calculate hash or checksum
Home-page: http://msztolcman.github.io/hashfile/
Author: Marcin Sztolcman
Author-email: marcin@urzenia.net
License: MIT
Keywords: security,hash,checksum,sha,sha1,md5,sha224,sha256,sha384,sha512,crc32,adler32,md4,mdc2,ripemd160,whirlpool
Platform: UNKNOWN
Classifier: Development Status :: 4 - Beta
Classifier: Environment :: Console
Classifier: Intended Audience :: Developers
Classifier: Intended Audience :: System Administrators
Classifier: License :: OSI Approved :: MIT License
Classifier: Topic :: Utilities
Classifier: Operating System :: OS Independent
Classifier: Programming Language :: Python :: 2.7
Classifier: Programming Language :: Python :: 3.3
Classifier: Programming Language :: Python :: 3.4
Classifier: Programming Language :: Python :: 3.5
Requires-Dist: argparse
